j2tpl/__init__.py
j2tpl/console/__init__.py
j2tpl/console/application.py
j2tpl/console/commands/__init__.py
j2tpl/console/commands/init.py
j2tpl/loaders/__init__.py
j2tpl/loaders/lazy_command_loader.py
j2tpl/parsers/__init__.py
j2tpl/parsers/json_parser.py
j2tpl/parsers/yaml_parser.py
j2tpl-2021.3.1.dist-info/entry_points.txt
j2tpl-2021.3.1.dist-info/LICENSE
j2tpl-2021.3.1.dist-info/WHEEL
j2tpl-2021.3.1.dist-info/METADATA
j2tpl-2021.3.1.dist-info/RECORD
