Metadata-Version: 2.1
Name: j2tpl
Version: 2021.3.1
Summary: 
License: MIT
Author: Janne K
Author-email: 0x022b@gmail.com
Requires-Python: >=3.8,<4.0
Classifier: License :: OSI Approved :: MIT License
Classifier: Programming Language :: Python :: 3
Classifier: Programming Language :: Python :: 3.8
Classifier: Programming Language :: Python :: 3.9
Requires-Dist: Jinja2 (>=2.11.3,<3.0.0)
Requires-Dist: cleo (==1.0.0a2)
